Workbook

Sheet Lista de Actividades
A1: PROYECTO: TuSuper en línea (TSL-2627) — LISTA DE ACTIVIDADES
A2: Consultora: Taracea | Grupo: PGPI-208 | Base normativa: NOR-11, NOR-21, NOR-22, NOR-25 | Plantilla oficial: LISTA DE ACTIVIDADES_v2.docx
A4: ID | B4: NOMBRE DE LA ACTIVIDAD | C4: DESCRIPCIÓN DEL TRABAJO | D4: ID PAQUETE EDT | E4: ELEMENTO (Texto1) | F4: ESTADO (Texto2) | G4: CÓDIGO MSP (Texto3) | H4: TIPO DE CUENTA / NATURALEZA
A5: ACT-01 | B5: Dirección de la planificación | C5: Gestión global de la fase de planificación, coordinación del equipo de expertos y elaboración del Plan de Dirección y Líneas Base. | D5: 1.1.1 | E5: — | F5: — | G5: DIR-PLA | H5: Dirección (Nivel de esfuerzo)
A6: ACT-02 | B6: Dirección y control del Sprint 1 | C6: Gestión de la ejecución del Sprint 1, seguimiento diario, eliminación de impedimentos y revisión/retrospectiva con el cliente. | D6: 1.1.2 | E6: — | F6: — | G6: SPR-01 | H6: Dirección (Nivel de esfuerzo)
A7: ACT-03 | B7: Dirección y control del Sprint 2 | C7: Gestión de la ejecución del Sprint 2, seguimiento diario y revisión/retrospectiva con el cliente. | D7: 1.1.3 | E7: — | F7: — | G7: SPR-02 | H7: Dirección (Nivel de esfuerzo)
A8: ACT-04 | B8: Dirección y control del Sprint 3 | C8: Gestión de la ejecución del Sprint 3, seguimiento diario y revisión/retrospectiva con el cliente. | D8: 1.1.4 | E8: — | F8: — | G8: SPR-03 | H8: Dirección (Nivel de esfuerzo)
A9: ACT-05 | B9: Dirección y control del Sprint 4 | C9: Gestión de la ejecución del Sprint 4, seguimiento diario y revisión/retrospectiva con el cliente. | D9: 1.1.5 | E9: — | F9: — | G9: SPR-04 | H9: Dirección (Nivel de esfuerzo)
A10: ACT-06 | B10: Dirección y control del Sprint 5 | C10: Gestión de la ejecución del Sprint 5, seguimiento diario y revisión/retrospectiva con el cliente. | D10: 1.1.6 | E10: — | F10: — | G10: SPR-05 | H10: Dirección (Nivel de esfuerzo)
A11: ACT-07 | B11: Dirección y control del Sprint 6 | C11: Gestión de la ejecución del Sprint 6, seguimiento diario y preparación del paso a producción. | D11: 1.1.7 | E11: — | F11: — | G11: SPR-06 | H11: Dirección (Nivel de esfuerzo)
A12: ACT-08 | B12: Cierre formal y liquidación | C12: Elaboración del informe de cierre, balance de líneas base, registro de lecciones aprendidas y liberación del personal. | D12: 1.1.8 | E12: — | F12: — | G12: CPR | H12: Dirección (Cierre)
A13: ACT-09 | B13: Traspaso al servicio de mantenimiento | C13: Traspaso del repositorio, configuración, relación de defectos abiertos y provisión para la garantía. | D13: 1.1.9 | E13: — | F13: — | G13: CPR | H13: Transición / Cierre
A14: ACT-10 | B14: Especificación funcional común | C14: Definición de especificaciones funcionales comunes y acuerdos de criterios de aceptación con TuSuper. | D14: 1.2.1.1 | E14: EP-01 | F14: — | G14: ESP-COM | H14: Transversal (EP-01)
A15: ACT-11 | B15: Diseño del sistema de interacción UI/UX | C15: Elaboración del sistema de diseño, pautas de interacción, maquetación base y componentes visuales comunes web y móvil. | D15: 1.2.1.2 | E15: EP-02 | F15: — | G15: DIS-UX | H15: Transversal (EP-02)
... A60: ACT-56 | B60: Formación de personal de tiendas piloto | C60: Impartición de las sesiones formativas al personal de las 3 tiendas piloto en el uso de la plataforma (FPI). | D60: 1.6.2.2 | E60: — | F60: — | G60: FPI | H60: Adquisición (Formación)

Sheet Resumen y Cobertura NOR-21
A1: RESUMEN DE COBERTURA Y CONFORMIDAD NORMATIVA (NOR-21 / NOR-11)
A2: Verificación de reglas mínimas para aceptación del cronograma por la Oficina de Proyectos
A4: REQUISITO FUNCIONAL | B4: NOMBRE DEL REQUISITO | C4: ESTADO E (ESP/DIS) | D4: ESTADO C (CONST/INT) | E4: ESTADO V (VERIF) | F4: TOTAL ACTIVIDADES | G4: ESTADO NOR-21
A5: RF-01 | B5: Autenticación de clientes con área personal | C5: =COUNTIFS('Lista de Actividades'!$E$5:$E$60, A5, 'Lista de Actividades'!$F$5:$F$60, "E") | D5: =COUNTIFS('Lista de Actividades'!$E$5:$E$60, A5, 'Lista de Actividades'!$F$5:$F$60, "C") | E5: =COUNTIFS('Lista de Actividades'!$E$5:$E$60, A5, 'Lista de Actividades'!$F$5:$F$60, "V") | F5: =SUM(C5:E5) | G5: =IF(AND(C5>=1, D5>=1, E5>=1), "CONFORME", "INCOMPLETO")
A6: RF-02 | B6: Catálogo de productos con búsqueda | C6: =COUNTIFS('Lista de Actividades'!$E$5:$E$60, A6, 'Lista de Actividades'!$F$5:$F$60, "E") | D6: =COUNTIFS('Lista de Actividades'!$E$5:$E$60, A6, 'Lista de Actividades'!$F$5:$F$60, "C") | E6: =COUNTIFS('Lista de Actividades'!$E$5:$E$60, A6, 'Lista de Actividades'!$F$5:$F$60, "V") | F6: =SUM(C6:E6) | G6: =IF(AND(C6>=1, D6>=1, E6>=1), "CONFORME", "INCOMPLETO")
A7: RF-03 | B7: Carrito de la compra persistente | C7: =COUNTIFS('Lista de Actividades'!$E$5:$E$60, A7, 'Lista de Actividades'!$F$5:$F$60, "E") | D7: =COUNTIFS('Lista de Actividades'!$E$5:$E$60, A7, 'Lista de Actividades'!$F$5:$F$60, "C") | E7: =COUNTIFS('Lista de Actividades'!$E$5:$E$60, A7, 'Lista de Actividades'!$F$5:$F$60, "V") | F7: =SUM(C7:E7) | G7: =IF(AND(C7>=1, D7>=1, E7>=1), "CONFORME", "INCOMPLETO")
A8: RF-04 | B8: Pago mediante pasarela externa | C8: =COUNTIFS('Lista de Actividades'!$E$5:$E$60, A8, 'Lista de Actividades'!$F$5:$F$60, "E") | D8: =COUNTIFS('Lista de Actividades'!$E$5:$E$60, A8, 'Lista de Actividades'!$F$5:$F$60, "C") | E8: =COUNTIFS('Lista de Actividades'!$E$5:$E$60, A8, 'Lista de Actividades'!$F$5:$F$60, "V") | F8: =SUM(C8:E8) | G8: =IF(AND(C8>=1, D8>=1, E8>=1), "CONFORME", "INCOMPLETO")
A9: RF-05 | B9: Logística de entrega por código postal | C9: =COUNTIFS('Lista de Actividades'!$E$5:$E$60, A9, 'Lista de Actividades'!$F$5:$F$60, "E") | D9: =COUNTIFS('Lista de Actividades'!$E$5:$E$60, A9, 'Lista de Actividades'!$F$5:$F$60, "C") | E9: =COUNTIFS('Lista de Actividades'!$E$5:$E$60, A9, 'Lista de Actividades'!$F$5:$F$60, "V") | F9: =SUM(C9:E9) | G9: =IF(AND(C9>=1, D9>=1, E9>=1), "CONFORME", "INCOMPLETO")
A10: RF-06 | B10: Panel de gestión de pedidos para tienda | C10: =COUNTIFS('Lista de Actividades'!$E$5:$E$60, A10, 'Lista de Actividades'!$F$5:$F$60, "E") | D10: =COUNTIFS('Lista de Actividades'!$E$5:$E$60, A10, 'Lista de Actividades'!$F$5:$F$60, "C") | E10: =COUNTIFS('Lista de Actividades'!$E$5:$E$60, A10, 'Lista de Actividades'!$F$5:$F$60, "V") | F10: =SUM(C10:E10) | G10: =IF(AND(C10>=1, D10>=1, E10>=1), "CONFORME", "INCOMPLETO")
A11: RF-07 | B11: Notificaciones por email y móvil | C11: =COUNTIFS('Lista de Actividades'!$E$5:$E$60, A11, 'Lista de Actividades'!$F$5:$F$60, "E") | D11: =COUNTIFS('Lista de Actividades'!$E$5:$E$60, A11, 'Lista de Actividades'!$F$5:$F$60, "C") | E11: =COUNTIFS('Lista de Actividades'!$E$5:$E$60, A11, 'Lista de Actividades'!$F$5:$F$60, "V") | F11: =SUM(C11:E11) | G11: =IF(AND(C11>=1, D11>=1, E11>=1), "CONFORME", "INCOMPLETO")
A12: RF-08 | B12: Informes básicos de ventas para dirección | C12: =COUNTIFS('Lista de Actividades'!$E$5:$E$60, A12, 'Lista de Actividades'!$F$5:$F$60, "E") | D12: =COUNTIFS('Lista de Actividades'!$E$5:$E$60, A12, 'Lista de Actividades'!$F$5:$F$60, "C") | E12: =COUNTIFS('Lista de Actividades'!$E$5:$E$60, A12, 'Lista de Actividades'!$F$5:$F$60, "V") | F12: =SUM(C12:E12) | G12: =IF(AND(C12>=1, D12>=1, E12>=1), "CONFORME", "INCOMPLETO")
A13: TOTAL FUNCIONALES | B13: 8 Requisitos Funcionales | C13: =SUM(C5:C12) | D13: =SUM(D5:D12) | E13: =SUM(E5:E12) | F13: =SUM(F5:F12) | G13: 100% CUMPLIDO
A16: DISTRIBUCIÓN TOTAL DE ACTIVIDADES POR NATURALEZA
A17: NATURALEZA / CATEGORÍA | B17: DESCRIPCIÓN NORMATIVA | C17: TOTAL ACTIVIDADES | D17: REQUISITO NOR-21
A18: Dirección del Proyecto | B18: Gestión de planificación, sprints 1 a 6 y cierre | C18: =COUNTIFS('Lista de Actividades'!$H$5:$H$60, "*Dirección*") | D18: Mínimo 1 paquete NDE
A19: Transición y Cierre | B19: Traspaso al mantenimiento y garantía | C19: =COUNTIFS('Lista de Actividades'!$H$5:$H$60, "*Transición*") | D19: Entregable obligatorio
A20: Requisitos Funcionales | B20: Estados E, C y V para RF-01 a RF-08 | C20: =COUNTIFS('Lista de Actividades'!$H$5:$H$60, "*Funcional*") | D20: Mínimo E, C, V por RF
A21: Elementos Transversales | B21: Tareas de EP-01 a EP-07 (Diseño, ERP, Despliegue, Doc) | C21: =COUNTIFS('Lista de Actividades'!$H$5:$H$60, "*Transversal*") | D21: Al menos 1 por EP
A22: Adquisiciones Externas e Internas | B22: Pedido, seguimiento y aceptación (Conector y Formación) | C22: =COUNTIFS('Lista de Actividades'!$H$5:$H$60, "*Adquisición*") | D22: Pedido, Seg y Acep
A23: Auditoría / Certificación Técnica | B23: Auditoría de pasarela de pago (15 días hábiles) | C23: =COUNTIFS('Lista de Actividades'!$H$5:$H$60, "*Certificación*") | D23: Hito técnico obligatorio
A24: TOTAL GENERAL ACTIVIDADES | B24: Alcance total descompuesto del proyecto TSL-2627 | C24: =SUM(C18:C23) | D24: CONFORME OFICINA PROYECTOS
